dc_common/__init__.py
dc_common/core/logger.py
dc_common/data_sources/__init__.py
dc_common/data_sources/base_source.py
dc_common/data_sources/daily_quote_source.py
dc_common/schemas/__init__.py
dc_common/schemas/a_stock.py
dc_common/schemas/base.py
dc_common/schemas/hk_announcement.py
dc_common/schemas/hk_company_profile.py
dc_common/schemas/hk_stock.py
dc_common/schemas/hs_industry.py
dc_common/schemas/hs_industry_company.py
dc_common/schemas/index_basic.py
dc_common/schemas/index_company.py
dc_common/schemas/index_daily.py
dc_common/schemas/margin_account.py
dc_common/schemas/margin_analysis.py
dc_common/schemas/margin_detail.py
dc_common/schemas/results.py
dc_common/schemas/sw_index_daily.py
dc_common/schemas/sw_industry.py
dc_common/schemas/sw_industry_company.py
dc_common/utils/auth_token.py
dc_common/utils/baidu_utils.py
dc_common/utils/cache_utils.py
dc_common/utils/config_reader.py
dc_common/utils/eastmoney_utils.py
dc_common/utils/jin10_utils.py
dc_common/utils/logging_config.py
dc_common/utils/markdown_convert.py
dc_common/utils/money_format.py
dc_common/utils/proxy_utils.py
dc_common/utils/schema_extract.py
dc_common/utils/xueqiu_utils.py
alpha_dc_common-0.1.24.dist-info/METADATA
alpha_dc_common-0.1.24.dist-info/WHEEL
alpha_dc_common-0.1.24.dist-info/RECORD
