Metadata-Version: 2.4
Name: alpha-dc-common
Version: 0.1.24
Summary: Shared schemas and utils for the datacenter project.
Author-email: Hang GuangLiang <hanguangliang@alphaaidig.com>
Requires-Dist: pydantic>=2.0
